score.mustache-0.1.3-py3.4-nspkg.pth
score/mustache/__init__.py
score/mustache/_init.py
score.mustache-0.1.3.dist-info/DESCRIPTION.rst
score.mustache-0.1.3.dist-info/METADATA
score.mustache-0.1.3.dist-info/RECORD
score.mustache-0.1.3.dist-info/WHEEL
score.mustache-0.1.3.dist-info/metadata.json
score.mustache-0.1.3.dist-info/namespace_packages.txt
score.mustache-0.1.3.dist-info/top_level.txt
